dominion_object_model/__init__.py
dominion_object_model/object_model.py
dominion_object_model-1.1.0.dist-info/LICENSE
dominion_object_model-1.1.0.dist-info/METADATA
dominion_object_model-1.1.0.dist-info/WHEEL
dominion_object_model-1.1.0.dist-info/top_level.txt
dominion_object_model-1.1.0.dist-info/RECORD
