Metadata-Version: 2.1
Name: dominion-object-model
Version: 1.1.0
Summary: abstract classes for implementing dominion players and clients
Home-page: https://github.com/the-gigi/dominion-object-model
Author: Gigi Sayfan
Author-email: the.gigi@gmail.com
License: MIT
Platform: UNKNOWN
Requires-Python: >=3.8
